FluViewer/FluViewer_v_0_3_8.py
FluViewer/__init__.py
fluviewer-0.3.8.dist-info/licenses/LICENSE
fluviewer-0.3.8.dist-info/METADATA
fluviewer-0.3.8.dist-info/WHEEL
fluviewer-0.3.8.dist-info/entry_points.txt
fluviewer-0.3.8.dist-info/top_level.txt
fluviewer-0.3.8.dist-info/RECORD
