Metadata-Version: 2.4
Name: FluViewer
Version: 0.3.8
Summary: An automated host- and subtype-agnostic tool for generating influenza A virus genome sequences from FASTQ data
Author-email: Kevin Kuchinski <kevin.kuchinski@gov.bc.ca>
License-Expression: MIT
Project-URL: Homepage, https://github.com/KevinKuchinski/FluViewer
Project-URL: Issues, https://github.com/KevinKuchinski/FluViewer/issues
Classifier: Programming Language :: Python :: 3
Classifier: Operating System :: OS Independent
Requires-Python: >=3.10
License-File: LICENSE
Dynamic: license-file
